Tensorflow20KuaisuRumenZhinanChuyiFix1/README.md
Tensorflow20KuaisuRumenZhinanChuyiFix1/__init__.py
Tensorflow20KuaisuRumenZhinanChuyiFix1/__main__.py
Tensorflow20KuaisuRumenZhinanChuyiFix1/file.epub
Tensorflow20KuaisuRumenZhinanChuyiFix1/index.html
Tensorflow20KuaisuRumenZhinanChuyiFix1/css/__init__.py
Tensorflow20KuaisuRumenZhinanChuyiFix1/css/annotations.css
Tensorflow20KuaisuRumenZhinanChuyiFix1/css/main.css
Tensorflow20KuaisuRumenZhinanChuyiFix1/css/normalize.css
Tensorflow20KuaisuRumenZhinanChuyiFix1/css/popup.css
Tensorflow20KuaisuRumenZhinanChuyiFix1/font/__init__.py
Tensorflow20KuaisuRumenZhinanChuyiFix1/font/fontello.eot
Tensorflow20KuaisuRumenZhinanChuyiFix1/font/fontello.svg
Tensorflow20KuaisuRumenZhinanChuyiFix1/font/fontello.ttf
Tensorflow20KuaisuRumenZhinanChuyiFix1/font/fontello.woff
Tensorflow20KuaisuRumenZhinanChuyiFix1/img/__init__.py
Tensorflow20KuaisuRumenZhinanChuyiFix1/img/annotator-glyph-sprite.png
Tensorflow20KuaisuRumenZhinanChuyiFix1/img/annotator-icon-sprite.png
Tensorflow20KuaisuRumenZhinanChuyiFix1/img/apple-touch-icon.png
Tensorflow20KuaisuRumenZhinanChuyiFix1/img/cancelfullscreen.png
Tensorflow20KuaisuRumenZhinanChuyiFix1/img/close.png
Tensorflow20KuaisuRumenZhinanChuyiFix1/img/fullscreen.png
Tensorflow20KuaisuRumenZhinanChuyiFix1/img/loader.gif
Tensorflow20KuaisuRumenZhinanChuyiFix1/img/menu-icon.png
Tensorflow20KuaisuRumenZhinanChuyiFix1/img/save.png
Tensorflow20KuaisuRumenZhinanChuyiFix1/img/saved.png
Tensorflow20KuaisuRumenZhinanChuyiFix1/img/settings-s.png
Tensorflow20KuaisuRumenZhinanChuyiFix1/img/settings.png
Tensorflow20KuaisuRumenZhinanChuyiFix1/img/star.png
Tensorflow20KuaisuRumenZhinanChuyiFix1/js/__init__.py
Tensorflow20KuaisuRumenZhinanChuyiFix1/js/epub.js
Tensorflow20KuaisuRumenZhinanChuyiFix1/js/epub.min.js
Tensorflow20KuaisuRumenZhinanChuyiFix1/js/epub.min.map
Tensorflow20KuaisuRumenZhinanChuyiFix1/js/hooks.min.js
Tensorflow20KuaisuRumenZhinanChuyiFix1/js/hooks.min.map
tensorflow_2_0_kuaisu_rumen_zhinan_chuyi_fix1-2025.3.24.1.dist-info/METADATA
tensorflow_2_0_kuaisu_rumen_zhinan_chuyi_fix1-2025.3.24.1.dist-info/WHEEL
tensorflow_2_0_kuaisu_rumen_zhinan_chuyi_fix1-2025.3.24.1.dist-info/entry_points.txt
tensorflow_2_0_kuaisu_rumen_zhinan_chuyi_fix1-2025.3.24.1.dist-info/top_level.txt
tensorflow_2_0_kuaisu_rumen_zhinan_chuyi_fix1-2025.3.24.1.dist-info/RECORD
